<?xml version="1.0" encoding="UTF-8" ?>
<bmtactionlog project="C:\Work\mdcirm\cognos\cirm_warehouse.cpf" templatedir="../templates/bmt/Cr1Model" timestamp="20141020095405684" user="SABBAS" version="10.1.6304.24"><transaction event="StartSession" saved="false" seq="1" timestamp="20141020095405685" uniqueId="C8D52F99C8D52F99" user="SABBAS"/><transaction saved="false" seq="2" timestamp="20141020095424869" uniqueId="6780E3AD6780E3AD"><action seq="1" type="SetActiveLocale"><inputparams><param seq="1" type="i18nstring"><value>en</value></param></inputparams><domchanges/><result success="t"><outputparams/></result></action></transaction></bmtactionlog>
